ez_excel_mgt-1.0.26.dist-info/METADATA
ez_excel_mgt-1.0.26.dist-info/WHEEL
ez_excel_mgt-1.0.26.dist-info/licenses/LICENSE
ez_excel_mgt/__init__.py
ez_excel_mgt/ez_excel_mgt.cpython-310-x86_64-linux-gnu.so
ez_excel_mgt-1.0.26.dist-info/RECORD
