Metadata-Version: 2.3
Name: ez_excel_mgt
Version: 1.0.26
License-File: LICENSE
Summary: A Rust-powered Python library for Excel file management and data manipulation
Home-Page: https://github.com/stoachup/ez-excel-mgt
Project-URL: Source Code, https://github.com/stoachup/ez-excel-mgt
